poli_sci_kit/__init__.py
poli_sci_kit/utils.py
poli_sci_kit/appointment/__init__.py
poli_sci_kit/appointment/checks.py
poli_sci_kit/appointment/methods.py
poli_sci_kit/appointment/metrics.py
poli_sci_kit/plot/__init__.py
poli_sci_kit/plot/dispr_bar.py
poli_sci_kit/plot/parliament.py
poli_sci_kit-1.1.0.dist-info/LICENSE.txt
poli_sci_kit-1.1.0.dist-info/METADATA
poli_sci_kit-1.1.0.dist-info/NOTICE.txt
poli_sci_kit-1.1.0.dist-info/WHEEL
poli_sci_kit-1.1.0.dist-info/top_level.txt
poli_sci_kit-1.1.0.dist-info/RECORD
