Metadata-Version: 2.1
Name: poli-sci-kit
Version: 1.1.0
Summary: Political elections, appointment, analysis and visualization in Python
Home-page: https://github.com/andrewtavis/poli-sci-kit
Author: Andrew Tavis McAllister
Author-email: andrew.t.mcallister@gmail.com
License: new BSD
Classifier: Development Status :: 5 - Production/Stable
Classifier: Intended Audience :: Developers
Classifier: Intended Audience :: Education
Classifier: Intended Audience :: Science/Research
Classifier: License :: OSI Approved :: BSD License
Classifier: Programming Language :: Python
Classifier: Programming Language :: Python :: 3
Classifier: Programming Language :: Python :: 3.8
Classifier: Programming Language :: Python :: 3.9
Classifier: Programming Language :: Python :: 3.10
Classifier: Programming Language :: Python :: 3.11
Classifier: Operating System :: OS Independent
Requires-Python: >=3.6
License-File: LICENSE.txt
License-File: NOTICE.txt
Requires-Dist: black >=19.10b0
Requires-Dist: colormath >=3.0.0
Requires-Dist: numpy >=1.19.2
Requires-Dist: packaging >=20.9
Requires-Dist: pandas >=1.2.1
Requires-Dist: pyOpenSSL >=20.0.1
Requires-Dist: pytest >=6.2.2
Requires-Dist: pytest-cov >=2.11.1
Requires-Dist: scipy >=1.5.2
Requires-Dist: seaborn >=0.11.1
